responses_proxy/__init__.py
responses_proxy/server.py
responses_proxy-0.1.4.dist-info/DESCRIPTION.rst
responses_proxy-0.1.4.dist-info/METADATA
responses_proxy-0.1.4.dist-info/RECORD
responses_proxy-0.1.4.dist-info/WHEEL
responses_proxy-0.1.4.dist-info/entry_points.txt
responses_proxy-0.1.4.dist-info/metadata.json
responses_proxy-0.1.4.dist-info/top_level.txt
