Metadata-Version: 2.0
Name: responses-proxy
Version: 0.1.4
Summary: allow you to easily mock HTTP responses in your tests
Home-page: https://github.com/bearstech/responses_proxy
Author: UNKNOWN
Author-email: UNKNOWN
License: UNKNOWN
Keywords: requests responses
Platform: UNKNOWN
Classifier: Development Status :: 3 - Alpha
Classifier: Intended Audience :: Developers
Classifier: Topic :: Software Development :: Testing
Classifier: License :: OSI Approved :: GNU General Public License v3 (GPLv3)
Classifier: Programming Language :: Python :: 2.7
Classifier: Programming Language :: Python :: 3.4
Classifier: Programming Language :: Python :: 3.5
Requires-Dist: requests
Requires-Dist: responses
Requires-Dist: waitress
Requires-Dist: webob
Provides-Extra: test
Requires-Dist: pytest; extra == 'test'
